eventzAPI/__init__.py
eventzAPI/eventzAPI.py
eventzAPI/flatArchiver.py
eventzapi_bobj-2.0.12.dist-info/LICENSE
eventzapi_bobj-2.0.12.dist-info/METADATA
eventzapi_bobj-2.0.12.dist-info/WHEEL
eventzapi_bobj-2.0.12.dist-info/top_level.txt
eventzapi_bobj-2.0.12.dist-info/RECORD
