Metadata-Version: 2.1
Name: eventzapi-bobj
Version: 2.0.12
Summary: The Events API supports a Python micro-services infrastructure
Home-page: https://www.eventzapi.com/
Author: I-Technology Inc.
Author-email: bobj@i-technologyinc.com
License: UNKNOWN
Platform: UNKNOWN
Classifier: Programming Language :: Python :: 3.8
Classifier: Natural Language :: English
Classifier: Topic :: System :: Distributed Computing
Classifier: Intended Audience :: Developers
Classifier: License :: OSI Approved :: GNU Lesser General Public License v3 or later (LGPLv3+)
Classifier: Operating System :: OS Independent
Requires-Python: >=3.8
